EscribaLogger/DPSingleton.py
EscribaLogger/Log.py
EscribaLogger/__init__.py
EscribaLogger/drivers/__init__.py
EscribaLogger/drivers/driver_file.py
EscribaLogger/drivers/driver_graylog.py
EscribaLogger/drivers/driver_stdout.py
EscribaLogger/process_extra_context.py
escribalogger-2.0.3.dist-info/METADATA
escribalogger-2.0.3.dist-info/WHEEL
escribalogger-2.0.3.dist-info/entry_points.txt
escribalogger-2.0.3.dist-info/licenses/LICENSE
escribalogger-2.0.3.dist-info/RECORD
