Metadata-Version: 2.1
Name: EscribaLogger
Version: 2.0.3
Summary: A fast 'read to use' Logging system which provides stdout/file/custom stream with easy syntax and operation. It's a very simple approach of Laravel drivers sorts, by the way, handlers ands drivers are both the same
Keywords: logging,logger,log,logs,drivers
Author-Email: Thiago Santa Clara Pereira <strovsk@outlook.com>
License: MIT
Classifier: Programming Language :: Python :: 3
Classifier: License :: OSI Approved :: MIT License
Classifier: Operating System :: OS Independent
Project-URL: Github, https://github.com/Strovsk/EscribaLogger
Requires-Python: >=3.10
Requires-Dist: markdown-it-py>=3.0.0
Requires-Dist: mdurl>=0.1.2
Requires-Dist: rich>=13.4.2
Requires-Dist: graypy>=2.1.0
